{
    "content": {
        "nocturnal_powder": { "type": "item", "content": "astralsorcery:nocturnal_powder", "amount": {"min": 8, "max": 16}, "unitWorth": 150, "rarity": "COMMON"},
        "illumination_powder": { "type": "item", "content": "astralsorcery:illumination_powder", "amount": {"min": 8, "max": 16}, "unitWorth": 150, "rarity": "COMMON"},
        "resonating_gem": { "type": "item", "content": "astralsorcery:resonating_gem", "amount": {"min": 1, "max": 2}, "unitWorth": 500, "rarity": "COMMON"},
        "stardust": { "type": "item", "content": "astralsorcery:stardust", "amount": {"min": 2, "max": 3}, "unitWorth": 350, "rarity": "COMMON"},
        "emerald": { "type": "item", "content": "minecraft:emerald", "amount": {"min": 8, "max": 32}, "unitWorth": 250, "rarity": "COMMON"},
        "chalk_gold": { "type": "item", "content": "occultism:chalk_gold", "amount": {"min": 1, "max": 1}, "unitWorth": 100, "rarity": "COMMON"},
        "chalk_white": { "type": "item", "content": "occultism:chalk_white", "amount": {"min": 1, "max": 1}, "unitWorth": 100, "rarity": "COMMON"},
        "cosmetic_botanist_emblem": { "type": "item", "content": "botania:cosmetic_botanist_emblem", "amount": {"min": 1, "max": 1}, "unitWorth": 250, "rarity": "COMMON"},
        "cosmetic_four_leaf_clover": { "type": "item", "content": "botania:cosmetic_four_leaf_clover", "amount": {"min": 1, "max": 1}, "unitWorth": 250, "rarity": "COMMON"},
        "cosmetic_unicorn_horn": { "type": "item", "content": "botania:cosmetic_unicorn_horn", "amount": {"min": 1, "max": 1}, "unitWorth": 250, "rarity": "COMMON"},
        "string": { "type": "item", "content": "minecraft:string", "amount": {"min": 8, "max": 16}, "unitWorth": 50, "rarity": "COMMON"},
        "fermented_spider_eye": { "type": "item", "content": "minecraft:fermented_spider_eye", "amount": {"min": 6, "max": 10}, "unitWorth": 50, "rarity": "COMMON"},
        "ender_pearl": { "type": "item", "content": "minecraft:ender_pearl", "amount": {"min": 1, "max": 1}, "unitWorth": 150, "rarity": "COMMON"},
        "red_mushroom": { "type": "item", "content": "minecraft:red_mushroom", "amount": {"min": 8, "max": 16}, "unitWorth": 50, "rarity": "COMMON"},
        "brown_mushroom": { "type": "item", "content": "minecraft:brown_mushroom", "amount": {"min": 8, "max": 16}, "unitWorth": 50, "rarity": "COMMON"},
        "phytogro": { "type": "item", "content": "thermal:phytogro", "amount": {"min": 8, "max": 16}, "unitWorth": 100, "rarity": "COMMON"},
        "tree_fertilizer": { "type": "item", "content": "create:tree_fertilizer", "amount": {"min": 8, "max": 16}, "unitWorth": 100, "rarity": "COMMON"},
        "fertilizer": { "type": "item", "content": "botania:fertilizer", "amount": {"min": 8, "max": 16}, "unitWorth": 100, "rarity": "COMMON"},
        "horn_grass": { "type": "item", "content": "botania:horn_grass", "amount": {"min": 1, "max": 1}, "unitWorth": 250, "rarity": "COMMON"},
        "lead_nugget": { "type": "item", "content": "emendatus:lead_nugget", "amount": {"min": 8, "max": 16}, "unitWorth": 150, "rarity": "COMMON"},
        "silver_nugget": { "type": "item", "content": "emendatus:silver_nugget", "amount": {"min": 8, "max": 16}, "unitWorth": 150, "rarity": "COMMON"},
        "arcane_gold_nugget": { "type": "item", "content": "eidolon:arcane_gold_nugget", "amount": {"min": 8, "max": 32}, "unitWorth": 50, "rarity": "COMMON"},
        "pewter_nugget": { "type": "item", "content": "eidolon:pewter_nugget", "amount": {"min": 8, "max": 16}, "unitWorth": 50, "rarity": "COMMON"},
        "token_sorrow": { "type": "item", "content": "naturesaura:token_sorrow", "amount": {"min": 1, "max": 1}, "unitWorth": 250, "rarity": "COMMON"},
        "token_anger": { "type": "item", "content": "naturesaura:token_anger", "amount": {"min": 1, "max": 1}, "unitWorth": 250, "rarity": "COMMON"},
        "token_fear": { "type": "item", "content": "naturesaura:token_fear", "amount": {"min": 1, "max": 1}, "unitWorth": 250, "rarity": "COMMON"},
        "token_joy": { "type": "item", "content": "naturesaura:token_joy", "amount": {"min": 1, "max": 1}, "unitWorth": 250, "rarity": "COMMON"},
        "gold_powder": { "type": "item", "content": "naturesaura:gold_powder", "amount": {"min": 1, "max": 1}, "unitWorth": 350, "rarity": "COMMON"},
        "gold_leaf": { "type": "item", "content": "naturesaura:gold_leaf", "amount": {"min": 1, "max": 1}, "unitWorth": 350, "rarity": "COMMON"},
        "void_jar": { "type": "item", "content": "ars_nouveau:void_jar", "amount": {"min": 1, "max": 1}, "unitWorth": 250, "rarity": "COMMON"},
        "wraith_heart": { "type": "item", "content": "eidolon:wraith_heart", "amount": {"min": 1, "max": 1}, "unitWorth": 100, "rarity": "COMMON"},
        "zombie_heart": { "type": "item", "content": "eidolon:zombie_heart", "amount": {"min": 1, "max": 1}, "unitWorth": 100, "rarity": "COMMON"},
        "book_restore": { "type": "item", "content": "darkutils:book_restore", "amount": {"min": 1, "max": 1}, "unitWorth": 250, "rarity": "COMMON"},
        "candle": { "type": "item", "content": "eidolon:candle", "amount": {"min": 8, "max": 12}, "unitWorth": 150, "rarity": "COMMON"}
    }
}